{
    "id": 105083635,
    "name": "markos dinglelust",
    "author": "Epon06",
    "creators": ["Epon06, KrazyFF"],
    "verifier": "KrazyFF",
    "verification": "https://youtu.be/EI3RJ3uZ_dI",
    "percentToQualify": "100",
    "password": "-",
    "records": [
        {
            "user": "Putte",
            "link": "https://medal.tv/games/geometry-dash/clips/ibzOz7HsyhDruVLPL/d1337ikOr9p9?invite=cr-MSxsTlosMjA5OTMyMzYyLA",
            "percent": 100,
            "hz": -1
        }
    ]
}
